raw/__init__.py
satip/__init__.py
satip/app.py
satip/constants.py
satip/data_store.py
satip/eumetsat.py
satip/filenames.py
satip/geospatial.py
satip/scale_to_zero_to_one.py
satip/serialize.py
satip/utils.py
satip-2.12.41.dist-info/licenses/LICENSE
satip-2.12.41.dist-info/METADATA
satip-2.12.41.dist-info/WHEEL
satip-2.12.41.dist-info/top_level.txt
satip-2.12.41.dist-info/RECORD
