Metadata-Version: 2.4
Name: satip
Version: 2.12.41
Summary: Satip provides the functionality necessary for
Author: Jacob Bieker, Ayrton Bourn, Jack Kelly
Author-email: info@openclimatefix.org
License: MIT
License-File: LICENSE
Requires-Dist: Cartopy==0.22.0
Requires-Dist: click==8.1.7
Requires-Dist: click-plugins==1.1.1
Requires-Dist: dask==2024.2.1
Requires-Dist: eumdac==2.2.1
Requires-Dist: freezegun==1.4.0
Requires-Dist: fsspec[s3]==2024.2.0
Requires-Dist: matplotlib==3.8.3
Requires-Dist: numcodecs==0.12.1
Requires-Dist: numpy==1.26.4
Requires-Dist: ocf-blosc2==0.0.4
Requires-Dist: pandas==2.2.1
Requires-Dist: psutil==5.9.8
Requires-Dist: pyproj==3.6.1
Requires-Dist: pyresample==1.28.2
Requires-Dist: pytest==8.0.2
Requires-Dist: requests==2.31.0
Requires-Dist: s3fs==2024.2.0
Requires-Dist: satpy==0.47.0
Requires-Dist: structlog==24.1.0
Requires-Dist: tqdm==4.66.2
Requires-Dist: typing_extensions==4.10.0
Requires-Dist: urllib3==1.26.18
Requires-Dist: xarray==2024.2.0
Requires-Dist: zarr==2.17.0
Requires-Dist: zipp==3.17.0
Requires-Dist: sentry-sdk
Dynamic: author
Dynamic: author-email
Dynamic: description
Dynamic: description-content-type
Dynamic: license
Dynamic: license-file
Dynamic: requires-dist
Dynamic: summary
